mkdocs_git_authors_plugin/__init__.py
mkdocs_git_authors_plugin/ci.py
mkdocs_git_authors_plugin/config.py
mkdocs_git_authors_plugin/exclude.py
mkdocs_git_authors_plugin/plugin.py
mkdocs_git_authors_plugin/util.py
mkdocs_git_authors_plugin/git/__init__.py
mkdocs_git_authors_plugin/git/author.py
mkdocs_git_authors_plugin/git/command.py
mkdocs_git_authors_plugin/git/commit.py
mkdocs_git_authors_plugin/git/page.py
mkdocs_git_authors_plugin/git/repo.py
mkdocs_git_authors_plugin-0.9.6.dist-info/licenses/LICENSE
mkdocs_git_authors_plugin-0.9.6.dist-info/METADATA
mkdocs_git_authors_plugin-0.9.6.dist-info/WHEEL
mkdocs_git_authors_plugin-0.9.6.dist-info/entry_points.txt
mkdocs_git_authors_plugin-0.9.6.dist-info/top_level.txt
mkdocs_git_authors_plugin-0.9.6.dist-info/RECORD
