Metadata-Version: 2.4
Name: mkdocs-git-authors-plugin
Version: 0.9.6
Summary: Mkdocs plugin to display git authors of a page
Author-email: Tim Vink <vinktim@gmail.com>
License: MIT
Project-URL: Homepage, https://github.com/timvink/mkdocs-git-authors-plugin
Keywords: mkdocs,git,contributors,committers,authors,plugin
Classifier: Operating System :: OS Independent
Classifier: Programming Language :: Python
Classifier: Programming Language :: Python :: 3
Classifier: Programming Language :: Python :: 3.8
Classifier: Programming Language :: Python :: 3.9
Classifier: Programming Language :: Python :: 3.10
Classifier: Programming Language :: Python :: 3.11
Classifier: Programming Language :: Python :: 3.12
Classifier: Programming Language :: Python :: 3.13
Classifier: Programming Language :: Python :: 3 :: Only
Classifier: License :: OSI Approved :: MIT License
Classifier: Topic :: Documentation
Classifier: Topic :: Text Processing
Requires-Python: >=3.8
License-File: LICENSE
Requires-Dist: mkdocs>=1.0
Dynamic: license-file
